fast_augment/__init__.py
fast_augment/core.py
fast_augment-0.1.6.dist-info/METADATA
fast_augment-0.1.6.dist-info/WHEEL
fast_augment-0.1.6.dist-info/top_level.txt
fast_augment-0.1.6.dist-info/RECORD
