Metadata-Version: 2.4
Name: fast_augment
Version: 0.1.6
Summary: One-command image augmentation
Home-page: https://github.com/aryanator/fastaugment
Author: Aryan Patil
Author-email: aryanator01@gmail.com
Classifier: Programming Language :: Python :: 3
Classifier: License :: OSI Approved :: MIT License
Requires-Python: >=3.6
Requires-Dist: numpy>=1.19.0
Requires-Dist: opencv-python>=4.5.0
Requires-Dist: tqdm>=4.0.0
